gammarer/aws_daily_cost_usage_reporter/__init__.py
gammarer/aws_daily_cost_usage_reporter/py.typed
gammarer/aws_daily_cost_usage_reporter/_jsii/__init__.py
gammarer/aws_daily_cost_usage_reporter/_jsii/aws-daily-cost-usage-reporter@1.2.35.jsii.tgz
gammarer_aws_daily_cost_usage_reporter-1.2.35.dist-info/LICENSE
gammarer_aws_daily_cost_usage_reporter-1.2.35.dist-info/METADATA
gammarer_aws_daily_cost_usage_reporter-1.2.35.dist-info/WHEEL
gammarer_aws_daily_cost_usage_reporter-1.2.35.dist-info/top_level.txt
gammarer_aws_daily_cost_usage_reporter-1.2.35.dist-info/RECORD
